jyx/__init__.py
jyx/jyx.py
jyx-0.0.3.dist-info/LICENSE
jyx-0.0.3.dist-info/METADATA
jyx-0.0.3.dist-info/WHEEL
jyx-0.0.3.dist-info/top_level.txt
jyx-0.0.3.dist-info/RECORD
