Metadata-Version: 2.1
Name: jyx
Version: 0.0.3
Summary: A simple text editor
Home-page: https://xitog.github.io/dgx/index.html
Author: Damien Gouteux
Author-email: damien.gouteux@gmail.com
Maintainer: Damien Gouteux
Maintainer-email: damien.gouteux@gmail.com
License: MIT
Keywords: jyx,editor,programming language,script,text
Platform: UNKNOWN
Classifier: Development Status :: 2 - Pre-Alpha
Classifier: License :: OSI Approved :: MIT License
Classifier: Operating System :: OS Independent
Classifier: Programming Language :: Python
Classifier: Programming Language :: Python :: 3 :: Only
Classifier: Programming Language :: Python :: Implementation :: CPython
Classifier: Topic :: Software Development
Classifier: Topic :: Text Editors
Requires-Python: >=3.5
